MANIFEST.in
setup.py
bin/pymarkdown
pymarkdown/__init__.py
pymarkdown/core.py
pymarkdown.egg-info/PKG-INFO
pymarkdown.egg-info/SOURCES.txt
pymarkdown.egg-info/dependency_links.txt
pymarkdown.egg-info/not-zip-safe
pymarkdown.egg-info/requires.txt
pymarkdown.egg-info/top_level.txt
pymarkdown/tests/test_core.py