Metadata-Version: 1.0
Name: pymarkdown
Version: 0.1.3
Summary: Evaluate code in markdown
Home-page: http://github.com/mrocklin/pymarkdown
Author: Matthew Rocklin
Author-email: mrocklin@gmail.com
License: BSD
Keywords: markdown documentation
Platform: UNKNOWN
